dolabra/__init__.py
dolabra/constants.py
dolabra/analysis/__init__.py
dolabra/analysis/symbolic.py
dolabra/analysis/module/__init__.py
dolabra/analysis/module/modules/__init__.py
dolabra/analysis/module/modules/basemodule.py
dolabra/analysis/module/modules/getter.py
dolabra/analysis/module/modules/loader.py
dolabra/analysis/module/modules/payable.py
dolabra/analysis/module/modules/setter.py
dolabra/analysis/module/modules/storage_caller_check.py
dolabra/analysis/module/modules/taints.py
dolabra/analysis/module/modules/token.py
dolabra/analysis/module/modules/utils.py
dolabra/benchmark/__init__.py
dolabra/benchmark/benchmark.py
dolabra/benchmark/contract_repository.py
dolabra/benchmark/flagged_function_repository.py
dolabra/benchmark/function_repository.py
dolabra/benchmark/verification_db.py
dolabra/cli/__init__.py
dolabra/cli/main.py
dolabra/contract_loaders/__init__.py
dolabra/contract_loaders/binary_loader.py
dolabra/contract_loaders/contract_loader.py
dolabra/contract_loaders/file_loader.py
dolabra/contract_loaders/jsonrpc_loader.py
dolabra/contract_loaders/loader.py
dolabra/contract_loaders/runtime_loader.py
dolabra/contract_loaders/solidity_loader.py
dolabra/logger/__init__.py
dolabra/logger/log_manager.py
dolabra-1.0.dist-info/METADATA
dolabra-1.0.dist-info/WHEEL
dolabra-1.0.dist-info/entry_points.txt
dolabra-1.0.dist-info/top_level.txt
dolabra-1.0.dist-info/RECORD
