Metadata-Version: 2.1
Name: dolabra
Version: 1.0
Summary: Semantic EVM bytecode analyzer based on Mythril
Home-page: https://github.com/davidloz/dolabra
Author: David Loz
Author-email: nicetry@gmail.com
License: MIT
Platform: UNKNOWN
Classifier: License :: OSI Approved :: MIT License
Classifier: Development Status :: 2 - Pre-Alpha
Classifier: Intended Audience :: Science/Research
Classifier: Programming Language :: Python :: 3.6
Classifier: Programming Language :: Python :: 3.7
Classifier: Programming Language :: Python :: 3.8
Classifier: Programming Language :: Python :: 3.9
Classifier: Programming Language :: Python :: 3.10
Requires-Python: >=3.7.0
Requires-Dist: Jinja2 ==2.11.2
Requires-Dist: mythril ==0.23.17
Requires-Dist: colorama ==0.4.3
Requires-Dist: pypandoc ==1.5
Requires-Dist: py-solc ==3.2.0
